WalletDecode.py
walletdecode-1.4.dist-info/LICENSE
walletdecode-1.4.dist-info/METADATA
walletdecode-1.4.dist-info/WHEEL
walletdecode-1.4.dist-info/RECORD
